mmp/__init__.py
mmp/__main__.py
mmp/cli/__init__.py
mmp/cli/__main__.py
mmp/cli/main_commands.py
mmp/cli/commands/__init__.py
mmp/cli/commands/get_config_command.py
mmp/cli/commands/get_recipe_command.py
mmp/cli/commands/inference_command.py
mmp/cli/commands/init_command.py
mmp/cli/commands/list_commands.py
mmp/cli/commands/serve_command.py
mmp/cli/commands/system_check_command.py
mmp/cli/commands/train_command.py
mmp/cli/templates/configs/config.yaml.j2
mmp/cli/templates/docker/Dockerfile.j2
mmp/cli/templates/docker/docker-compose.yml.j2
mmp/cli/templates/project/.gitignore
mmp/cli/templates/project/README.md.j2
mmp/cli/templates/project/SETUP.md.j2
mmp/cli/templates/project/pyproject.toml.j2
mmp/cli/templates/recipes/recipe.yaml.j2
mmp/cli/utils/__init__.py
mmp/cli/utils/cli_progress.py
mmp/cli/utils/config_builder.py
mmp/cli/utils/env_loader.py
mmp/cli/utils/header.py
mmp/cli/utils/interactive_ui.py
mmp/cli/utils/recipe_builder.py
mmp/cli/utils/system_checker.py
mmp/cli/utils/template_engine.py
mmp/components/__init__.py
mmp/components/base_registry.py
mmp/components/adapter/__init__.py
mmp/components/adapter/base.py
mmp/components/adapter/registry.py
mmp/components/adapter/modules/__init__.py
mmp/components/adapter/modules/feast_adapter.py
mmp/components/adapter/modules/sql_adapter.py
mmp/components/adapter/modules/storage_adapter.py
mmp/components/calibration/__init__.py
mmp/components/calibration/base.py
mmp/components/calibration/calibration_evaluator.py
mmp/components/calibration/registry.py
mmp/components/calibration/modules/__init__.py
mmp/components/calibration/modules/beta_calibration.py
mmp/components/calibration/modules/isotonic_regression.py
mmp/components/datahandler/__init__.py
mmp/components/datahandler/base.py
mmp/components/datahandler/catalog_utils.py
mmp/components/datahandler/registry.py
mmp/components/datahandler/modules/sequence_handler.py
mmp/components/datahandler/modules/tabular_handler.py
modern_ml_pipeline-1.2.1.dist-info/METADATA
modern_ml_pipeline-1.2.1.dist-info/WHEEL
modern_ml_pipeline-1.2.1.dist-info/entry_points.txt
modern_ml_pipeline-1.2.1.dist-info/licenses/LICENSE
modern_ml_pipeline-1.2.1.dist-info/RECORD
