Metadata-Version: 2.4
Name: modern-ml-pipeline
Version: 1.2.1
Summary: A modern, yaml-driven ML pipeline for multiple models.
Project-URL: Homepage, https://github.com/wooshikwon/modern-ml-pipeline
Project-URL: Issues, https://github.com/wooshikwon/modern-ml-pipeline/issues
Project-URL: Repository, https://github.com/wooshikwon/modern-ml-pipeline
Author-email: wooshikwon <wooshikwon@github.com>
License:                                  Apache License
License-File: LICENSE
Classifier: License :: OSI Approved :: MIT License
Classifier: Operating System :: OS Independent
Classifier: Programming Language :: Python :: 3
Requires-Python: <3.14,>=3.10
Requires-Dist: boto3>=1.20.0
Requires-Dist: category-encoders>=2.8.1
Requires-Dist: fastapi
Requires-Dist: google-cloud-bigquery>=3.12.0
Requires-Dist: google-cloud-storage>=2.0.0
Requires-Dist: httpx>=0.28.1
Requires-Dist: jinja2
Requires-Dist: mlflow<4,>=3
Requires-Dist: optuna>=3.0.0
Requires-Dist: packaging>=24.2
Requires-Dist: pandas
Requires-Dist: prometheus-fastapi-instrumentator>=7.0.0
Requires-Dist: psycopg[binary]>=3.2.9
Requires-Dist: pyarrow
Requires-Dist: pydantic>=2.0.0
Requires-Dist: python-dotenv
Requires-Dist: pyyaml
Requires-Dist: redis>=6.2.0
Requires-Dist: rich>=14.0.0
Requires-Dist: rtdl-revisiting-models>=0.0.2
Requires-Dist: scikit-learn
Requires-Dist: scipy>=1.10.0
Requires-Dist: setuptools>=68
Requires-Dist: shap>=0.41.0
Requires-Dist: sqlalchemy>=2.0.0
Requires-Dist: typer
Requires-Dist: uvicorn[standard]
Requires-Dist: xgboost>=1.7.0
Provides-Extra: all
Requires-Dist: catboost>=1.2.0; extra == 'all'
Requires-Dist: db-dtypes>=1.0.0; extra == 'all'
Requires-Dist: feast>=0.35.0; extra == 'all'
Requires-Dist: fsspec>=2024.0.0; extra == 'all'
Requires-Dist: gcsfs>=2025.5.1; extra == 'all'
Requires-Dist: google-cloud-bigquery-storage>=2.24.0; extra == 'all'
Requires-Dist: lightgbm>=4.1.0; extra == 'all'
Requires-Dist: llvmlite>=0.41.1; extra == 'all'
Requires-Dist: numba>=0.58.1; extra == 'all'
Requires-Dist: s3fs>=2025.5.1; extra == 'all'
Requires-Dist: sqlalchemy-bigquery>=1.9.0; extra == 'all'
Requires-Dist: torch>=2.0.0; extra == 'all'
Provides-Extra: cloud-extras
Requires-Dist: db-dtypes>=1.0.0; extra == 'cloud-extras'
Requires-Dist: fsspec>=2024.0.0; extra == 'cloud-extras'
Requires-Dist: gcsfs>=2025.5.1; extra == 'cloud-extras'
Requires-Dist: google-cloud-bigquery-storage>=2.24.0; extra == 'cloud-extras'
Requires-Dist: s3fs>=2025.5.1; extra == 'cloud-extras'
Requires-Dist: sqlalchemy-bigquery>=1.9.0; extra == 'cloud-extras'
Provides-Extra: dev
Requires-Dist: import-linter>=2.3.0; extra == 'dev'
Requires-Dist: ipykernel>=6.0.0; extra == 'dev'
Requires-Dist: mypy>=1.8.0; extra == 'dev'
Requires-Dist: pre-commit>=3.0.0; extra == 'dev'
Requires-Dist: psutil>=5.9.0; extra == 'dev'
Requires-Dist: psycopg2-binary>=2.9.9; extra == 'dev'
Requires-Dist: pytest-cov>=6.2.1; extra == 'dev'
Requires-Dist: pytest-json-report>=1.5.0; extra == 'dev'
Requires-Dist: pytest-timeout>=2.3.1; extra == 'dev'
Requires-Dist: pytest-xdist>=3.8.0; extra == 'dev'
Requires-Dist: pytest>=8.0.0; extra == 'dev'
Requires-Dist: ruff>=0.12.0; extra == 'dev'
Provides-Extra: feature-store
Requires-Dist: feast>=0.35.0; extra == 'feature-store'
Provides-Extra: ml-extras
Requires-Dist: catboost>=1.2.0; extra == 'ml-extras'
Requires-Dist: lightgbm>=4.1.0; extra == 'ml-extras'
Requires-Dist: llvmlite>=0.41.1; extra == 'ml-extras'
Requires-Dist: numba>=0.58.1; extra == 'ml-extras'
Provides-Extra: torch-extras
Requires-Dist: torch>=2.0.0; extra == 'torch-extras'
